ReGrid-0.0.3.dist-info/METADATA
ReGrid-0.0.3.dist-info/RECORD
ReGrid-0.0.3.dist-info/WHEEL
ReGrid-0.0.3.dist-info/top_level.txt
regrid/__init__.py
regrid/flowgrid/FlowGrid.py
regrid/flowgrid/SUTRA.py
regrid/flowgrid/__init__.py
regrid/gui/__init__.py
regrid/gui/main_ui.py
regrid/gui/regridGUI.py
